logits_processor_zoo/transformers/__init__.py
logits_processor_zoo/transformers/base.py
logits_processor_zoo/transformers/cite_prompt.py
logits_processor_zoo/transformers/generation_length.py
logits_processor_zoo/transformers/last_phrase.py
logits_processor_zoo/transformers/max_time.py
logits_processor_zoo/transformers/multiple_choice.py
logits_processor_zoo/transformers/prevent_hallucination.py
logits_processor_zoo/transformers/trigger_phrase.py
logits_processor_zoo/trtllm/__init__.py
logits_processor_zoo/trtllm/cite_prompt.py
logits_processor_zoo/trtllm/generation_length.py
logits_processor_zoo/trtllm/last_phrase.py
logits_processor_zoo/trtllm/max_time.py
logits_processor_zoo/trtllm/multiple_choice.py
logits_processor_zoo/trtllm/prevent_hallucination.py
logits_processor_zoo/trtllm/trigger_phrase.py
logits_processor_zoo/utils.py
logits_processor_zoo/vllm/__init__.py
logits_processor_zoo/vllm/cite_prompt.py
logits_processor_zoo/vllm/generation_length.py
logits_processor_zoo/vllm/last_phrase.py
logits_processor_zoo/vllm/max_time.py
logits_processor_zoo/vllm/multiple_choice.py
logits_processor_zoo/vllm/prevent_hallucination.py
logits_processor_zoo/vllm/trigger_phrase.py
logits_processor_zoo-0.2.1.dist-info/LICENSE
logits_processor_zoo-0.2.1.dist-info/METADATA
logits_processor_zoo-0.2.1.dist-info/WHEEL
logits_processor_zoo-0.2.1.dist-info/RECORD
