Metadata-Version: 2.1
Name: logits-processor-zoo
Version: 0.2.1
Summary: A collection of LogitsProcessors to customize and enhance LLM behavior for specific tasks.
Author: Ahmet Erdem
Requires-Python: >=3.10
Classifier: Programming Language :: Python :: 3
Classifier: Programming Language :: Python :: 3.10
Classifier: Programming Language :: Python :: 3.11
Classifier: Programming Language :: Python :: 3.12
Provides-Extra: vllm
Requires-Dist: accelerate (>=0.26.1)
Requires-Dist: torch
Requires-Dist: transformers (>=4.41.2)
Requires-Dist: vllm (>=0.5.0.post1) ; extra == "vllm"
